maiden/__init__.py
maiden/main.py
maiden/source1.yaml
maiden/templates/my_template.md
maiden-0.2.4.dist-info/METADATA
maiden-0.2.4.dist-info/WHEEL
maiden-0.2.4.dist-info/entry_points.txt
maiden-0.2.4.dist-info/top_level.txt
maiden-0.2.4.dist-info/RECORD
