Metadata-Version: 2.1
Name: maiden
Version: 0.2.4
Summary: A tool to generate Markdown files from templates populated with data from YAML or JSON files.
Home-page: https://github.com/gomleksiz/maiden
Author: Huseyin Gomleksizoglu
Author-email: huseyim@gmail.com
Classifier: Programming Language :: Python :: 3
Classifier: License :: OSI Approved :: MIT License
Classifier: Operating System :: OS Independent
Requires-Python: >=3.6
Requires-Dist: click
Requires-Dist: pyyaml
Requires-Dist: jinja2
